inferi/__init__.py
inferi/datasets.py
inferi/exceptions.py
inferi/series.py
inferi/variables.py
inferi-0.4.0.dist-info/DESCRIPTION.rst
inferi-0.4.0.dist-info/METADATA
inferi-0.4.0.dist-info/RECORD
inferi-0.4.0.dist-info/WHEEL
inferi-0.4.0.dist-info/metadata.json
inferi-0.4.0.dist-info/top_level.txt
